cloudservices_arg/__init__.py
cloudservices_arg/config/__init__.py
cloudservices_arg/config/cloud_config.py
cloudservices_arg/queueservice/__init__.py
cloudservices_arg/queueservice/pubsub.py
cloudservices_arg/queueservice/queue.py
cloudservices_arg/queueservice/sqs.py
cloudservices_arg/storageservice/__init__.py
cloudservices_arg/storageservice/storage.py
cloudservices_arg-0.1.11.dist-info/METADATA
cloudservices_arg-0.1.11.dist-info/WHEEL
cloudservices_arg-0.1.11.dist-info/top_level.txt
cloudservices_arg-0.1.11.dist-info/RECORD
